TeleBee/__init__.py
telebee-1.1.dist-info/LICENSE.txt
telebee-1.1.dist-info/METADATA
telebee-1.1.dist-info/WHEEL
telebee-1.1.dist-info/top_level.txt
telebee-1.1.dist-info/RECORD
