Metadata-Version: 2.2
Name: TeleBee
Version: 1.1
Summary: A Python library for organizing and loading bot functions from external files for the Telebot library. Simplifies bot code management by allowing the use of separate files for bot commands and functions.
Home-page: https://t.me/midoghanam
Author: Mohammed Ahmed Ghanam
Author-email: Mohamed Ahmed Ghanam <mghanam883@outlook.com>
License: MIT
Project-URL: Homepage, https://t.me/mido_ghanam
Project-URL: TelegramChannel, https://t.me/midoghanam
Project-URL: EgyptianProgrammers, https://t.me/egyptionprogrammers
Project-URL: Whatsapp, https://wa.me/201101023681
Requires-Python: >=3.6
License-File: LICENSE.txt
Dynamic: author
Dynamic: home-page
Dynamic: requires-python
